{"identification":{"description":"This overrides the countryScheme. Specifies the Local Jurisdiction that            applies to a Transaction, for example for the purposes of defining which Local Taxes            will apply.","publicationDate":"2013-01-15","shortName":"localJurisdictionScheme","version":"1-1","canonicalUri":"http://www.fpml.org/coding-scheme/local-jurisdiction","canonicalVersionUri":"http://www.fpml.org/coding-scheme/local-jurisdiction-1-1","locationUri":"http://www.fpml.org/coding-scheme/local-jurisdiction-1-1.xml"},"codes":[{"value":"Afghanistan","description":"Afghan Local Jurisdiction applies.","source":"FpML","effectiveDate":"2013-01-15"},{"value":"Applicable","description":"Follows Local Jurisdiction as per MCA to this Transaction.","source":"FpML","effectiveDate":"2013-01-15"},{"value":"Australia","description":"Australian Local Jurisdiction applies.","source":"FpML","effectiveDate":"2013-01-15"},{"value":"China","description":"Chinese Local Jurisdiction applies.","source":"FpML","effectiveDate":"2013-01-15"},{"value":"HongKong","description":"Hong Kong Local Jurisdiction applies.","source":"FpML","effectiveDate":"2013-01-15"},{"value":"India","description":"Indian Local Jurisdiction applies.","source":"FpML","effectiveDate":"2013-01-15"},{"value":"Indonesia","description":"Indonesian Local Jurisdiction applies.","source":"FpML","effectiveDate":"2013-01-15"},{"value":"Japan","description":"Japanese Local Jurisdiction applies.","source":"FpML","effectiveDate":"2013-01-15"},{"value":"Korea","description":"Korean Local Jurisdiction applies.","source":"FpML","effectiveDate":"2013-01-15"},{"value":"Malaysia","description":"Malaysian Local Jurisdiction applies.","source":"FpML","effectiveDate":"2013-01-15"},{"value":"NewZealand","description":"New Zealand Local Jurisdiction applies.","source":"FpML","effectiveDate":"2013-01-15"},{"value":"NotApplicable","description":"No Local Jurisdiction applies to this Transaction.","source":"FpML","effectiveDate":"2013-01-15"},{"value":"Pakistan","description":"Pakistani Local Jurisdiction applies.","source":"FpML","effectiveDate":"2013-01-15"},{"value":"Philippines","description":"Philippine Local Jurisdiction applies.","source":"FpML","effectiveDate":"2013-01-15"},{"value":"Singapore","description":"Singaporean Local Jurisdiction applies.","source":"FpML","effectiveDate":"2013-01-15"},{"value":"Taiwan","description":"Taiwanese Local Jurisdiction applies.","source":"FpML","effectiveDate":"2013-01-15"},{"value":"Thailand","description":"Thai Local Jurisdiction applies.","source":"FpML","effectiveDate":"2013-01-15"},{"value":"Vietnam","description":"Vietnamese Local Jurisdiction applies.","source":"FpML","effectiveDate":"2013-01-15"}]}