{
  "trade" : {
    "tradeIdentifier" : [ {
      "issuerReference" : {
        "globalReference" : "33f59567",
        "externalReference" : "PartyA"
      },
      "assignedIdentifier" : [ {
        "identifier" : {
          "value" : "Bond1",
          "meta" : {
            "scheme" : "http://www.PartyA.com/eqd-trade-id"
          }
        }
      } ],
      "meta" : {
        "globalKey" : "10ca1193"
      }
    } ],
    "tradeDate" : {
      "value" : "2004-12-24",
      "meta" : {
        "globalKey" : "3ea318"
      }
    },
    "tradableProduct" : {
      "product" : {
        "contractualProduct" : {
          "productTaxonomy" : [ {
            "source" : "ISDA",
            "productQualifier" : "InterestRate_Option_DebtOption"
          } ],
          "economicTerms" : {
            "payout" : {
              "optionPayout" : [ {
                "payerReceiver" : {
                  "payer" : "Party2",
                  "receiver" : "Party1"
                },
                "priceQuantity" : {
                  "quantitySchedule" : {
                    "address" : {
                      "scope" : "DOCUMENT",
                      "value" : "quantity-1"
                    }
                  },
                  "meta" : {
                    "globalKey" : "0"
                  }
                },
                "settlementTerms" : {
                  "settlementType" : "Physical",
                  "settlementCurrency" : {
                    "value" : "JPY"
                  },
                  "settlementDate" : {
                    "adjustableOrRelativeDate" : {
                      "relativeDate" : {
                        "periodMultiplier" : 8,
                        "period" : "D",
                        "meta" : {
                          "globalKey" : "bfe34747"
                        },
                        "dayType" : "Business",
                        "businessDayConvention" : "NONE",
                        "businessCenters" : {
                          "businessCenter" : [ {
                            "value" : "GBLO"
                          }, {
                            "value" : "JPTO"
                          } ],
                          "meta" : {
                            "globalKey" : "42a8663"
                          }
                        },
                        "dateRelativeTo" : {
                          "globalReference" : "2da32bc1",
                          "externalReference" : "EXERCISE"
                        }
                      }
                    },
                    "meta" : {
                      "globalKey" : "bfe34747"
                    }
                  },
                  "meta" : {
                    "globalKey" : "95fcb1"
                  }
                },
                "buyerSeller" : {
                  "buyer" : "Party1",
                  "seller" : "Party2"
                },
                "optionType" : "Call",
                "exerciseTerms" : {
                  "optionStyle" : {
                    "americanExercise" : {
                      "commencementDate" : {
                        "adjustableDate" : {
                          "unadjustedDate" : "2004-12-29",
                          "dateAdjustments" : {
                            "businessDayConvention" : "FOLLOWING",
                            "businessCenters" : {
                              "businessCenter" : [ {
                                "value" : "GBLO"
                              }, {
                                "value" : "JPTO"
                              } ],
                              "meta" : {
                                "globalKey" : "42a8663"
                              }
                            },
                            "meta" : {
                              "globalKey" : "da506292"
                            }
                          },
                          "meta" : {
                            "globalKey" : "dc6674d5"
                          }
                        },
                        "meta" : {
                          "globalKey" : "dc6674d5"
                        }
                      },
                      "expirationDate" : {
                        "adjustableDate" : {
                          "unadjustedDate" : "2009-06-01",
                          "dateAdjustments" : {
                            "businessDayConvention" : "FOLLOWING",
                            "businessCenters" : {
                              "businessCenter" : [ {
                                "value" : "GBLO"
                              }, {
                                "value" : "JPTO"
                              } ],
                              "meta" : {
                                "globalKey" : "42a8663"
                              }
                            },
                            "meta" : {
                              "globalKey" : "da506292"
                            }
                          },
                          "meta" : {
                            "globalKey" : "dd0515f1"
                          }
                        },
                        "meta" : {
                          "globalKey" : "dd0515f1"
                        }
                      },
                      "earliestExerciseTime" : {
                        "hourMinuteTime" : "09:00:00",
                        "businessCenter" : {
                          "value" : "GBLO"
                        }
                      },
                      "expirationTime" : {
                        "hourMinuteTime" : "16:00:00",
                        "businessCenter" : {
                          "value" : "GBLO"
                        }
                      },
                      "multipleExercise" : {
                        "integralMultipleAmount" : 1,
                        "minimumNumberOfOptions" : 20,
                        "maximumNumberOfOptions" : 200
                      },
                      "meta" : {
                        "globalKey" : "2da32bc1",
                        "externalKey" : "EXERCISE"
                      }
                    }
                  },
                  "strike" : {
                    "referenceSwapCurve" : {
                      "swapUnwindValue" : {
                        "floatingRateIndex" : "JPY-LIBOR-BBA",
                        "indexTenor" : {
                          "periodMultiplier" : 6,
                          "period" : "M",
                          "meta" : {
                            "globalKey" : "107"
                          }
                        },
                        "spread" : 27
                      }
                    }
                  },
                  "exerciseProcedure" : {
                    "manualExercise" : {
                      "exerciseNotice" : {
                        "exerciseNoticeGiver" : "Seller",
                        "businessCenter" : {
                          "value" : "GBLO"
                        }
                      }
                    },
                    "followUpConfirmation" : true,
                    "limitedRightToConfirm" : false,
                    "splitTicket" : true
                  }
                },
                "underlier" : {
                  "security" : {
                    "productIdentifier" : [ {
                      "address" : {
                        "scope" : "DOCUMENT",
                        "value" : "productIdentifier-1"
                      }
                    } ],
                    "securityType" : "Debt"
                  },
                  "meta" : {
                    "globalKey" : "1ff493"
                  }
                },
                "meta" : {
                  "globalKey" : "3a906a95"
                }
              } ],
              "meta" : {
                "globalKey" : "3a906a95"
              }
            },
            "calculationAgent" : {
              "calculationAgentParty" : "CalculationAgentIndependent"
            }
          },
          "meta" : {
            "globalKey" : "246c023f"
          }
        },
        "meta" : {
          "globalKey" : "246c023f"
        }
      },
      "tradeLot" : [ {
        "priceQuantity" : [ {
          "quantity" : [ {
            "value" : {
              "value" : 200,
              "unit" : {
                "financialUnit" : "Contract"
              },
              "multiplier" : {
                "value" : 10000000,
                "unit" : {
                  "currency" : {
                    "value" : "JPY"
                  }
                }
              }
            },
            "meta" : {
              "location" : [ {
                "scope" : "DOCUMENT",
                "value" : "quantity-1"
              } ]
            }
          } ],
          "observable" : {
            "productIdentifier" : [ {
              "value" : {
                "identifier" : {
                  "value" : "ExampleISIN2",
                  "meta" : {
                    "scheme" : "ISIN"
                  }
                },
                "source" : "ISIN",
                "meta" : {
                  "globalKey" : "63b037b6"
                }
              },
              "meta" : {
                "location" : [ {
                  "scope" : "DOCUMENT",
                  "value" : "productIdentifier-1"
                } ]
              }
            } ],
            "meta" : {
              "globalKey" : "1256bf0a"
            }
          },
          "settlementTerms" : {
            "settlementType" : "Physical",
            "meta" : {
              "globalKey" : "f3b1d0d7"
            }
          },
          "meta" : {
            "globalKey" : "21e09831"
          }
        } ]
      } ],
      "counterparty" : [ {
        "role" : "Party1",
        "partyReference" : {
          "globalReference" : "33f59568",
          "externalReference" : "PartyB"
        }
      }, {
        "role" : "Party2",
        "partyReference" : {
          "globalReference" : "33f59567",
          "externalReference" : "PartyA"
        }
      } ],
      "ancillaryParty" : [ {
        "role" : "CalculationAgentIndependent",
        "partyReference" : [ {
          "globalReference" : "33f59567",
          "externalReference" : "PartyA"
        } ]
      } ]
    },
    "party" : [ {
      "partyId" : [ {
        "identifier" : {
          "value" : "Party A",
          "meta" : {
            "scheme" : "http://www.fpml.org/coding-scheme/dummy-party-id"
          }
        },
        "meta" : {
          "globalKey" : "33f59567"
        }
      } ],
      "meta" : {
        "globalKey" : "33f59567",
        "externalKey" : "PartyA"
      }
    }, {
      "partyId" : [ {
        "identifier" : {
          "value" : "Party B",
          "meta" : {
            "scheme" : "http://www.fpml.org/coding-scheme/dummy-party-id"
          }
        },
        "meta" : {
          "globalKey" : "33f59568"
        }
      } ],
      "meta" : {
        "globalKey" : "33f59568",
        "externalKey" : "PartyB"
      }
    } ],
    "meta" : {
      "globalKey" : "b3d51443"
    }
  },
  "meta" : {
    "globalKey" : "b3d51443"
  }
}