{
  "agreementDate": "2022-03-21",
  "agreementTerms": {
    "agreement": {
      "creditSupportAgreementElections": {
        "CreditSupportAgreementVariationMarginElections": {
          "additionalRepresentations": {
            "additionalRepresentation": {
              "partyElection": [
                {
                  "isApplicable": false,
                  "party": "PARTY_1"
                },
                {
                  "isApplicable": false,
                  "party": "PARTY_2"
                }
              ]
            }
          },
          "baseAndEligibleCurrency": {
            "baseCurrency": "USD",
            "baseCurrencyTerminationCurrency": false,
            "eligibleCurrencyInclBaseCurrency": true
          },
          "calculationAndTiming": {
            "notificationTime": {
              "partyElections": [
                {
                  "localBusinessDay": true,
                  "notificationTime": {
                    "businessCenter": {
                      "value": "USNY"
                    },
                    "hourMinuteTime": "10:00:00"
                  },
                  "party": "PARTY_1"
                },
                {
                  "localBusinessDay": true,
                  "notificationTime": {
                    "businessCenter": {
                      "value": "USNY"
                    },
                    "hourMinuteTime": "10:00:00"
                  },
                  "party": "PARTY_2"
                }
              ]
            },
            "valuationAgent": {
              "party": "PARTY_2"
            },
            "valuationDate": {
              "date": "EACH",
              "day": "LOCAL_BUSINESS_DAY",
              "frequency": "DAILY"
            },
            "valuationDateLocation": {
              "partyElection": [
                {
                  "businessCenter": {
                    "value": "USNY"
                  },
                  "party": "PARTY_1"
                },
                {
                  "businessCenter": {
                    "value": "KYGE"
                  },
                  "party": "PARTY_2"
                }
              ]
            },
            "valuationTime": {
              "day": "PREVIOUS_LOCAL_BUSINESS_DAY",
              "time": "CLOSE_OF_BUSINESS"
            }
          },
          "conditionsPrecedent": {
            "specifiedConditionOrAccessCondition": {
              "isApplicable": true,
              "partyElection": [
                {
                  "party": "PARTY_1",
                  "specifiedOrAccessCondition": [
                    "ILLEGALITY",
                    "FORCE_MAJEURE_EVENT",
                    "TAX_EVENT"
                  ]
                },
                {
                  "party": "PARTY_2",
                  "specifiedOrAccessCondition": [
                    "ILLEGALITY",
                    "FORCE_MAJEURE_EVENT",
                    "TAX_EVENT"
                  ]
                }
              ]
            }
          },
          "coveredTransactions": {
            "bespokeCoveredTransactions": [
              "Fx Spot Transactions & Physically Settled Fx Forward Transactions"
            ],
            "exposure": {
              "partyElection": [
                {
                  "excludedProducts": [
                    {
                      "excluded": false,
                      "product": [
                        "FX_SETTLEMENT_DATE"
                      ]
                    }
                  ],
                  "excludedTransactions": true,
                  "party": "PARTY_1"
                },
                {
                  "excludedProducts": [
                    {
                      "excluded": false,
                      "product": [
                        "FX_SETTLEMENT_DATE"
                      ]
                    }
                  ],
                  "excludedTransactions": true,
                  "party": "PARTY_2"
                }
              ]
            }
          },
          "creditSupportObligations": {
            "collateralTransferTiming": {
              "transferSettlementTiming": {
                "cashCollateralTransferSettlementTime": "SAME"
              }
            },
            "deliveryAmount": {
              "deliveryAmount": "STANDARD"
            },
            "eligibleCreditSupport": {
              "partyElection": [
                {
                  "asPermitted": false,
                  "eligibleCollateral": [
                    {
                      "collateralCriteria": {
                        "AssetType": {
                          "assetType": "CASH"
                        }
                      },
                      "treatment": {
                        "isIncluded": true,
                        "valuationTreatment": {
                          "marginPercentage": 100
                        }
                      }
                    }
                  ],
                  "otherEligibleSupport": "Not Applicable",
                  "party": "PARTY_1"
                },
                {
                  "asPermitted": false,
                  "eligibleCollateral": [
                    {
                      "collateralCriteria": {
                        "AssetType": {
                          "assetType": "CASH"
                        }
                      },
                      "treatment": {
                        "isIncluded": true,
                        "valuationTreatment": {
                          "marginPercentage": 100
                        }
                      }
                    }
                  ],
                  "otherEligibleSupport": "Not Applicable",
                  "party": "PARTY_2"
                }
              ]
            },
            "fxHaircut": "Standard",
            "ineligibleCreditSupport": {
              "specifiedParty": [
                "PARTY_1"
              ],
              "totalIneligibilityDate": "Standard",
              "transferIneligibilityDate": "Standard"
            },
            "majorCurrency": [
              {
                "value": "USD"
              },
              {
                "value": "CAD"
              },
              {
                "value": "EUR"
              },
              {
                "value": "GBP"
              },
              {
                "value": "JPY"
              },
              {
                "value": "CHF"
              },
              {
                "value": "NZD"
              },
              {
                "value": "AUD"
              },
              {
                "value": "SEK"
              },
              {
                "value": "DKK"
              },
              {
                "value": "NOK"
              }
            ],
            "minimumTransferAmount": {
              "partyElection": [
                {
                  "fixedAmount": {
                    "amount": {
                      "unit": {
                        "currency": {
                          "value": "USD"
                        }
                      },
                      "value": 150000
                    },
                    "event": [
                      "EVENT_OF_DEFAULT"
                    ],
                    "zeroEvent": true
                  },
                  "party": "PARTY_1"
                },
                {
                  "fixedAmount": {
                    "amount": {
                      "unit": {
                        "currency": {
                          "value": "USD"
                        }
                      },
                      "value": 150000
                    },
                    "event": [
                      "EVENT_OF_DEFAULT"
                    ],
                    "zeroEvent": true
                  },
                  "party": "PARTY_2"
                }
              ]
            },
            "returnAmount": {
              "returnAmount": "STANDARD"
            },
            "rounding": {
              "currency": "USD",
              "deliveryAmount": 10000,
              "deliveryDirection": "UP",
              "returnAmount": 10000,
              "returnDirection": "DOWN"
            }
          },
          "creditSupportOffsets": false,
          "demandsAndNotices": {
            "deemedEffectiveNextLBD": false,
            "partyElection": [
              {
                "partyReference": "PARTY_1",
                "primaryContactInformation": {
                  "additionalInformation": "Senior Vice President, Collateral Management",
                  "address": [
                    {
                      "city": "London",
                      "country": {
                        "value": "United Kingdom"
                      },
                      "postalCode": "EC3V 9AA",
                      "street": [
                        "10 Lombard Street"
                      ]
                    }
                  ],
                  "email": [
                    "abc@xyz.com"
                  ],
                  "telephone": [
                    {
                      "number": "+44 20 7946 8800",
                      "telephoneNumberType": "WORK"
                    },
                    {
                      "number": "+44 20 7946 8899",
                      "telephoneNumberType": "FAX"
                    }
                  ]
                }
              },
              {
                "partyReference": "PARTY_2",
                "primaryContactInformation": {
                  "additionalInformation": "Margining Officer",
                  "address": [
                    {
                      "country": {
                        "value": "Cayman Island"
                      },
                      "street": [
                        "Harbor View Centre, 4th Floor, 129 Seaview Road"
                      ]
                    }
                  ],
                  "email": [
                    "colmgmt@Nexus.com"
                  ],
                  "telephone": [
                    {
                      "number": "+1 (345) 623-9100",
                      "telephoneNumberType": "WORK"
                    },
                    {
                      "number": "+1 (345) 623-9101",
                      "telephoneNumberType": "FAX"
                    }
                  ]
                }
              }
            ]
          },
          "disputeResolution": {
            "legacyAlternative": {
              "resolutionAlternative": "NO_ALTERNATIVE"
            },
            "resolutionTime": {
              "businessCenter": {
                "value": "USNY"
              },
              "hourMinuteTime": "01:00:00"
            },
            "value": {
              "cash": "CASH_PERCENTAGE_LESS_HAIRCUT"
            }
          },
          "distributionAndInterestPayment": {
            "interestParameters": [
              {
                "currency": "USD",
                "interestCalculationParameters": {
                  "compoundingType": "NONE",
                  "dayCountFraction": "ACT_360",
                  "floatingRate": {
                    "compressibleSpread": false,
                    "negativeInterest": true,
                    "rateOption": {
                      "value": {
                        "FloatingRateIndex": {
                          "assetClass": "INTEREST_RATE",
                          "floatingRateIndex": {
                            "value": "USD_FEDERAL_FUNDS"
                          },
                          "identifier": [
                            {
                              "identifier": {
                                "value": "USD"
                              },
                              "identifierType": "CURRENCY_CODE"
                            }
                          ],
                          "assetType": "Other"
                        }
                      }
                    }
                  },
                  "inBaseCurrency": false
                },
                "interestHandlingParameters": {
                  "alternativeToInterestAmount": "STANDARD",
                  "includeAccrualInMarginCalc": false,
                  "interestPaymentHandling": "TRANSFER_OR_ADJUST",
                  "netInterestWithMarginCalls": true,
                  "netPostedAndHeldInterest": true,
                  "onFullReturn": false,
                  "onPartialReturn": false
                },
                "marginType": "VARIATION_MARGIN"
              }
            ]
          },
          "finalReturns": {
            "applicable": false
          },
          "holdingAndUsingPostedCollateral": {
            "partyElection": [
              {
                "eligibilityToHoldCollateral": {
                  "custodianEligibility": false
                },
                "party": "PARTY_1",
                "useOfPostedCollateral": true
              },
              {
                "eligibilityToHoldCollateral": {
                  "custodianEligibility": false
                },
                "party": "PARTY_2",
                "useOfPostedCollateral": true
              }
            ]
          },
          "masterAgreementDatedAsOfDate": {
            "masterAgreementDatedAsOfDate": "2022-03-21"
          },
          "otherAgreements": {
            "otherCSA": {
              "isSpecified": false
            }
          },
          "otherEligibleAndPostedSupport": {
            "applicableTransfer": false,
            "applicableValue": false
          },
          "securityInterestForObligations": {
            "obligations": "NOT_APPLICABLE",
            "obligee": "OTHER",
            "other": "Not applicable",
            "party": [
              "PARTY_1",
              "PARTY_2"
            ]
          },
          "substitution": {
            "partyElection": [
              {
                "needsConsent": true,
                "party": "PARTY_1",
                "substitutionDateLanguage": "Standard"
              },
              {
                "needsConsent": true,
                "party": "PARTY_2",
                "substitutionDateLanguage": "Standard"
              }
            ]
          }
        }
      }
    },
    "counterparty": [
      {
        "partyReference": {
          "value": {
            "name": {
              "value": "Sterling Bank Ltd"
            },
            "partyId": [
              {
                "identifier": {
                  "value": "ABCD1234"
                },
                "identifierType": "LEI"
              }
            ]
          }
        },
        "role": "PARTY_1"
      },
      {
        "partyReference": {
          "value": {
            "name": {
              "value": "Crestpoint Investment Fund LP"
            },
            "partyId": [
              {
                "identifier": {
                  "value": "1234ABCD"
                },
                "identifierType": "LEI"
              }
            ]
          }
        },
        "role": "PARTY_2"
      }
    ]
  },
  "contractualParty": [
    {
      "value": {
        "name": {
          "value": "Sterling Bank Ltd"
        },
        "partyId": [
          {
            "identifier": {
              "value": "ABCD1234"
            },
            "identifierType": "LEI"
          }
        ]
      }
    },
    {
      "value": {
        "name": {
          "value": "Crestpoint Investment Fund LP"
        },
        "partyId": [
          {
            "identifier": {
              "value": "1234ABCD"
            },
            "identifierType": "LEI"
          }
        ]
      }
    }
  ],
  "legalAgreementIdentification": {
    "agreementName": {
      "agreementType": "CREDIT_SUPPORT_AGREEMENT",
      "creditSupportAgreementMarginType": "VARIATION_MARGIN",
      "creditSupportAgreementType": {
        "value": "CREDIT_SUPPORT_ANNEX"
      }
    },
    "governingLaw": "USNY",
    "publisher": "ISDA",
    "vintage": 2016
  }
}