{
  "trade" : {
    "product" : {
      "taxonomy" : [ {
        "source" : "ISDA",
        "productQualifier" : "CreditDefaultSwap_SingleName"
      } ],
      "economicTerms" : {
        "effectiveDate" : {
          "adjustableDate" : {
            "unadjustedDate" : "2002-12-05",
            "dateAdjustments" : {
              "businessDayConvention" : "NONE",
              "meta" : {
                "globalKey" : "24a738"
              }
            },
            "meta" : {
              "globalKey" : "eb0a8cfd"
            }
          },
          "meta" : {
            "globalKey" : "eb0a8cfd"
          }
        },
        "terminationDate" : {
          "adjustableDate" : {
            "unadjustedDate" : "2007-12-05",
            "dateAdjustments" : {
              "businessDayConvention" : "MODFOLLOWING",
              "businessCenters" : {
                "businessCenter" : [ {
                  "value" : "GBLO"
                }, {
                  "value" : "USNY"
                }, {
                  "value" : "JPTO"
                } ],
                "meta" : {
                  "globalKey" : "81e56a96"
                }
              },
              "meta" : {
                "globalKey" : "58681de7"
              }
            },
            "meta" : {
              "globalKey" : "28faf882"
            }
          },
          "meta" : {
            "globalKey" : "28faf882"
          }
        },
        "dateAdjustments" : {
          "businessDayConvention" : "MODFOLLOWING",
          "businessCenters" : {
            "businessCenter" : [ {
              "value" : "GBLO"
            }, {
              "value" : "USNY"
            }, {
              "value" : "JPTO"
            } ],
            "meta" : {
              "globalKey" : "81e56a96"
            }
          },
          "meta" : {
            "globalKey" : "58681de7"
          }
        },
        "payout" : [ {
          "CreditDefaultPayout" : {
            "payerReceiver" : {
              "payer" : "Party1",
              "receiver" : "Party2"
            },
            "priceQuantity" : {
              "quantitySchedule" : {
                "address" : {
                  "scope" : "DOCUMENT",
                  "value" : "quantity-1"
                }
              },
              "meta" : {
                "globalKey" : "0"
              }
            },
            "settlementTerms" : {
              "settlementType" : "Physical",
              "settlementCurrency" : {
                "value" : "JPY"
              },
              "meta" : {
                "globalKey" : "b6b5f8e2"
              },
              "physicalSettlementTerms" : {
                "physicalSettlementPeriod" : {
                  "businessDays" : 30
                },
                "deliverableObligations" : {
                  "accruedInterest" : false,
                  "category" : "BondOrLoan",
                  "notSubordinated" : true,
                  "specifiedCurrency" : {
                    "applicable" : true
                  },
                  "notContingent" : true,
                  "assignableLoan" : {
                    "applicable" : true
                  },
                  "consentRequiredLoan" : {
                    "applicable" : true
                  },
                  "transferable" : true,
                  "maximumMaturity" : {
                    "periodMultiplier" : 30,
                    "period" : "Y",
                    "meta" : {
                      "globalKey" : "3fb"
                    }
                  },
                  "notBearer" : true
                },
                "escrow" : true,
                "meta" : {
                  "globalKey" : "944a7af8"
                }
              }
            },
            "generalTerms" : {
              "referenceInformation" : {
                "referenceEntity" : {
                  "entityId" : [ {
                    "value" : "004CC9",
                    "meta" : {
                      "scheme" : "http://www.fpml.org/spec/2003/entity-id-RED-1-0"
                    }
                  } ],
                  "name" : {
                    "value" : "ACOM CO., LTD."
                  },
                  "entityIdentifier" : [ {
                    "identifier" : {
                      "value" : "004CC9",
                      "meta" : {
                        "scheme" : "http://www.fpml.org/spec/2003/entity-id-RED-1-0"
                      }
                    },
                    "identifierType" : "REDID",
                    "meta" : {
                      "globalKey" : "44b3e4c7"
                    }
                  } ],
                  "meta" : {
                    "globalKey" : "a47e3ab4",
                    "externalKey" : "referenceEntity"
                  }
                },
                "referenceObligation" : [ {
                  "security" : {
                    "identifier" : [ {
                      "identifier" : {
                        "value" : "JP310860A032",
                        "meta" : {
                          "scheme" : "http://www.fpml.org/spec/2002/instrument-id-ISIN-1-0"
                        }
                      },
                      "identifierType" : "ISIN"
                    } ],
                    "instrumentType" : "Debt"
                  },
                  "primaryObligorReference" : {
                    "globalReference" : "a47e3ab4",
                    "externalReference" : "referenceEntity"
                  }
                } ],
                "allGuarantees" : true,
                "referencePrice" : {
                  "value" : 1,
                  "unit" : {
                    "currency" : {
                      "value" : "JPY"
                    }
                  },
                  "perUnitOf" : {
                    "currency" : {
                      "value" : "JPY"
                    }
                  },
                  "priceType" : "AssetPrice"
                }
              },
              "modifiedEquityDelivery" : true
            },
            "protectionTerms" : [ {
              "creditEvents" : {
                "restructuring" : {
                  "applicable" : true,
                  "multipleHolderObligation" : true,
                  "multipleCreditEventNotices" : true
                },
                "creditEventNotice" : {
                  "notifyingParty" : [ "Party2", "Party1" ],
                  "businessCenter" : "GBLO",
                  "publiclyAvailableInformation" : {
                    "standardPublicSources" : true,
                    "specifiedNumber" : 2
                  }
                },
                "meta" : {
                  "globalKey" : "a12d3685"
                }
              },
              "obligations" : {
                "category" : "BorrowedMoney",
                "notSubordinated" : true
              },
              "meta" : {
                "globalKey" : "b67a88d5"
              }
            } ]
          },
          "meta" : {
            "globalKey" : "c0d030d7"
          }
        }, {
          "InterestRatePayout" : {
            "payerReceiver" : {
              "payer" : "Party2",
              "receiver" : "Party1"
            },
            "priceQuantity" : {
              "quantitySchedule" : {
                "address" : {
                  "scope" : "DOCUMENT",
                  "value" : "quantity-2"
                }
              },
              "meta" : {
                "globalKey" : "0"
              }
            },
            "rateSpecification" : {
              "FixedRateSpecification" : {
                "rateSchedule" : {
                  "price" : {
                    "address" : {
                      "scope" : "DOCUMENT",
                      "value" : "price-1"
                    }
                  }
                },
                "meta" : {
                  "globalKey" : "0"
                }
              }
            },
            "dayCountFraction" : {
              "value" : "ACT/360"
            },
            "calculationPeriodDates" : {
              "calculationPeriodFrequency" : {
                "periodMultiplier" : 3,
                "period" : "M",
                "meta" : {
                  "globalKey" : "204c"
                },
                "rollConvention" : "5"
              },
              "meta" : {
                "globalKey" : "204c"
              }
            },
            "paymentDates" : {
              "paymentFrequency" : {
                "periodMultiplier" : 3,
                "period" : "M",
                "meta" : {
                  "globalKey" : "aa"
                }
              },
              "firstPaymentDate" : "2003-03-05",
              "meta" : {
                "globalKey" : "3ead5b"
              }
            }
          },
          "meta" : {
            "globalKey" : "4f992e8e"
          }
        } ],
        "calculationAgent" : {
          "calculationAgentParty" : "CalculationAgentIndependent",
          "calculationAgentBusinessCenter" : {
            "value" : "GBLO"
          }
        }
      },
      "meta" : {
        "globalKey" : "89f41635"
      }
    },
    "tradeLot" : [ {
      "priceQuantity" : [ {
        "price" : [ {
          "value" : {
            "value" : 0.007,
            "unit" : {
              "currency" : {
                "value" : "JPY"
              }
            },
            "perUnitOf" : {
              "currency" : {
                "value" : "JPY"
              }
            },
            "priceType" : "InterestRate"
          },
          "meta" : {
            "location" : [ {
              "scope" : "DOCUMENT",
              "value" : "price-1"
            } ]
          }
        } ],
        "quantity" : [ {
          "value" : {
            "value" : 500000000,
            "unit" : {
              "currency" : {
                "value" : "JPY"
              }
            }
          },
          "meta" : {
            "location" : [ {
              "scope" : "DOCUMENT",
              "value" : "quantity-2"
            } ]
          }
        } ],
        "meta" : {
          "globalKey" : "790f635e"
        }
      }, {
        "quantity" : [ {
          "value" : {
            "value" : 500000000,
            "unit" : {
              "currency" : {
                "value" : "JPY"
              }
            }
          },
          "meta" : {
            "location" : [ {
              "scope" : "DOCUMENT",
              "value" : "quantity-1"
            } ]
          }
        } ],
        "meta" : {
          "globalKey" : "11fe4b42"
        }
      } ]
    } ],
    "counterparty" : [ {
      "role" : "Party1",
      "partyReference" : {
        "globalReference" : "b3f9d7f4",
        "externalReference" : "party1"
      }
    }, {
      "role" : "Party2",
      "partyReference" : {
        "globalReference" : "9f870959",
        "externalReference" : "party2"
      }
    } ],
    "ancillaryParty" : [ {
      "role" : "CalculationAgentIndependent",
      "partyReference" : [ {
        "globalReference" : "b3f9d7f4",
        "externalReference" : "party1"
      } ]
    } ],
    "tradeIdentifier" : [ {
      "issuerReference" : {
        "globalReference" : "b3f9d7f4",
        "externalReference" : "party1"
      },
      "assignedIdentifier" : [ {
        "identifier" : {
          "value" : "37209",
          "meta" : {
            "scheme" : "http://www.swapswire.com/spec/2001/trade-id-1-0"
          }
        },
        "version" : 1
      } ],
      "meta" : {
        "globalKey" : "73faee95"
      }
    } ],
    "tradeDate" : {
      "value" : "2002-12-04",
      "meta" : {
        "globalKey" : "3e9304"
      }
    },
    "party" : [ {
      "partyId" : [ {
        "identifier" : {
          "value" : "254900BIAQJIUV6DLE92",
          "meta" : {
            "scheme" : "http://www.fpml.org/coding-scheme/external/iso17442"
          }
        },
        "identifierType" : "LEI",
        "meta" : {
          "globalKey" : "664adf91"
        }
      } ],
      "name" : {
        "value" : "XYZ Bank"
      },
      "meta" : {
        "globalKey" : "b3f9d7f4",
        "externalKey" : "party1"
      }
    }, {
      "partyId" : [ {
        "identifier" : {
          "value" : "549300VBWWV6BYQOWM67",
          "meta" : {
            "scheme" : "http://www.fpml.org/coding-scheme/external/iso17442"
          }
        },
        "identifierType" : "LEI",
        "meta" : {
          "globalKey" : "4a5d2d9f"
        }
      } ],
      "name" : {
        "value" : "ABC Bank"
      },
      "meta" : {
        "globalKey" : "9f870959",
        "externalKey" : "party2"
      }
    } ],
    "contractDetails" : {
      "documentation" : [ {
        "legalAgreementIdentification" : {
          "agreementName" : {
            "agreementType" : "MasterAgreement",
            "masterAgreementType" : {
              "value" : "ISDAMaster"
            }
          },
          "vintage" : 1992
        },
        "contractualParty" : [ {
          "globalReference" : "b3f9d7f4",
          "externalReference" : "party1"
        }, {
          "globalReference" : "9f870959",
          "externalReference" : "party2"
        } ],
        "meta" : {
          "globalKey" : "55171602"
        }
      }, {
        "legalAgreementIdentification" : {
          "agreementName" : {
            "agreementType" : "Confirmation",
            "contractualDefinitionsType" : [ {
              "value" : "ISDA2003CreditDerivatives"
            } ],
            "contractualTermsSupplement" : [ {
              "contractualTermsSupplementType" : {
                "value" : "ISDA2003CreditMay2003"
              }
            } ],
            "contractualMatrix" : [ {
              "matrixType" : {
                "value" : "CreditDerivativesPhysicalSettlementMatrix"
              }
            } ]
          }
        },
        "contractualParty" : [ {
          "globalReference" : "b3f9d7f4",
          "externalReference" : "party1"
        }, {
          "globalReference" : "9f870959",
          "externalReference" : "party2"
        } ],
        "meta" : {
          "globalKey" : "8f493f4f"
        }
      } ],
      "meta" : {
        "globalKey" : "d587250d"
      }
    },
    "meta" : {
      "globalKey" : "8752327f"
    }
  },
  "meta" : {
    "globalKey" : "8752327f"
  }
}