{
  "options": {
    "FIS_TRADE": {
      "name": "FIS_TRADE",
      "modelId": "COMMON-DOMAIN-MODEL",
      "modelClasspath": ["model","cdm/rosetta"],
      "modelFileDirIncludeRegex": ".*\\.rosetta",
      "modelFileDirExcludeRegex": null,
      "rosettaClasses": ["WorkflowStep"],
      "generatedPackage": "fis",
      "generatedFactoryName": "FisXmlHandlerFactory",
      "xsdFilePaths": {"WorkflowStep": "schemas/fis/fis.xsd"},
      "synonymSources": {"WorkflowStep": ["FIS"]},
      "topLevelTags": {},
      "verbose": false,
      "clean": false,
      "json": false,
      "cdmClassesDir": "",
      "integrationTestRoots": {
        "WorkflowStep": [
          "cdm-sample-files/fis"
        ]
      },
      "default": true,
      "childPackageName": {"WorkflowStep": "fis"},
      "fullClassnames": {"WorkflowStep": "cdm.event.workflow.WorkflowStep"}
    }
  }
}
