{
  "action" : "NEW",
  "eventIdentifier" : [ {
    "issuerReference" : {
      "globalReference" : "280bb774",
      "externalReference" : "DTCC00001234"
    },
    "meta" : {
      "globalKey" : "0"
    }
  }, {
    "issuerReference" : {
      "globalReference" : "4d851ed1",
      "externalReference" : "DTCC00005678"
    },
    "meta" : {
      "globalKey" : "0"
    }
  } ],
  "messageInformation" : {
    "messageId" : {
      "value" : "MSERV20181008.0004086555",
      "meta" : {
        "scheme" : "perFpMLReqmt"
      }
    },
    "sentBy" : {
      "value" : "MarkitSERV"
    },
    "sentTo" : [ {
      "value" : "DTCC"
    } ]
  },
  "meta" : {
    "globalKey" : "85cfd9bc"
  },
  "party" : [ {
    "meta" : {
      "globalKey" : "280bb774",
      "externalKey" : "DTCC00001234"
    },
    "partyId" : [ {
      "value" : "DTCC00001234",
      "meta" : {
        "scheme" : "DTCC"
      }
    }, {
      "value" : "DTCCZBUT11V806EZRVTWT807",
      "meta" : {
        "scheme" : "http://www.fpml.org/coding-scheme/external/iso17442"
      }
    } ]
  }, {
    "meta" : {
      "globalKey" : "4d851ed1",
      "externalKey" : "DTCC00005678"
    },
    "partyId" : [ {
      "value" : "DTCC00005678",
      "meta" : {
        "scheme" : "DTCC"
      }
    }, {
      "value" : "DTCC7H6GLXDRUGQFU57RNE97",
      "meta" : {
        "scheme" : "http://www.fpml.org/coding-scheme/external/iso17442"
      }
    } ]
  } ],
  "timestamp" : [ {
    "dateTime" : "2018-10-08T05:57:52.137-05:00",
    "qualification" : "EVENT_SUBMITTED_DATE_TIME"
  }, {
    "dateTime" : "2018-10-08T10:58:02.462Z",
    "qualification" : "EVENT_CREATION_DATE_TIME"
  } ]
}